{
  "project_info": {
    "project_number": "533637351693",
    "firebase_url": "https://student-care-fb29b.firebaseio.com",
    "project_id": "student-care-fb29b",
    "storage_bucket": "student-care-fb29b.appspot.com"
  },
  "client": [
    {
      "client_info": {
        "mobilesdk_app_id": "1:533637351693:android:05d8bf19e37c440d",
        "android_client_info": {
          "package_name": "com.abcd.studentcare"
        }
      },
      "oauth_client": [],
      "api_key": [
        {
          "current_key": "AIzaSyASN_ESnUT8GxCUkqwiK01j8v5EEJNjixM"
        }
      ],
      "services": {
        "appinvite_service": {
          "other_platform_oauth_client": [
            {
              "client_id": "533637351693-8asv8mqkmp9d799pm36a1oct76anrf5e.apps.googleusercontent.com",
              "client_type": 3
            }
          ]
        }
      }
    }
  ],
  "configuration_version": "1"
}